bin/examples/persistence_example
bin/examples/plugin_usage_example
bin/examples/table_design_demo
include/gmock/gmock-actions.h
include/gmock/gmock-cardinalities.h
include/gmock/gmock-function-mocker.h
include/gmock/gmock-matchers.h
include/gmock/gmock-more-actions.h
include/gmock/gmock-more-matchers.h
include/gmock/gmock-nice-strict.h
include/gmock/gmock-spec-builders.h
include/gmock/gmock.h
include/gmock/internal/custom/README.md
include/gmock/internal/custom/gmock-generated-actions.h
include/gmock/internal/custom/gmock-matchers.h
include/gmock/internal/custom/gmock-port.h
include/gmock/internal/gmock-internal-utils.h
include/gmock/internal/gmock-port.h
include/gmock/internal/gmock-pp.h
include/gtest/gtest-assertion-result.h
include/gtest/gtest-death-test.h
include/gtest/gtest-matchers.h
include/gtest/gtest-message.h
include/gtest/gtest-param-test.h
include/gtest/gtest-printers.h
include/gtest/gtest-spi.h
include/gtest/gtest-test-part.h
include/gtest/gtest-typed-test.h
include/gtest/gtest.h
include/gtest/gtest_pred_impl.h
include/gtest/gtest_prod.h
include/gtest/internal/custom/README.md
include/gtest/internal/custom/gtest-port.h
include/gtest/internal/custom/gtest-printers.h
include/gtest/internal/custom/gtest.h
include/gtest/internal/gtest-death-test-internal.h
include/gtest/internal/gtest-filepath.h
include/gtest/internal/gtest-internal.h
include/gtest/internal/gtest-param-util.h
include/gtest/internal/gtest-port-arch.h
include/gtest/internal/gtest-port.h
include/gtest/internal/gtest-string.h
include/gtest/internal/gtest-type-util.h
include/sage_tsdb/plugins/adapters/fault_detection_adapter.h
include/sage_tsdb/plugins/adapters/pecj_adapter.h
include/sage_tsdb/plugins/event_bus.h
include/sage_tsdb/plugins/plugin_interface.h
include/sage_tsdb/plugins/plugin_manager.h
include/sage_tsdb/plugins/plugin_registry.h
lib/cmake/GTest/GTestConfig.cmake
lib/cmake/GTest/GTestConfigVersion.cmake
lib/cmake/GTest/GTestTargets-release.cmake
lib/cmake/GTest/GTestTargets.cmake
isage_tsdb-0.1.5.dist-info/METADATA
isage_tsdb-0.1.5.dist-info/WHEEL
isage_tsdb-0.1.5.dist-info/licenses/LICENSE
isage_tsdb-0.1.5.dist-info/RECORD
