Metadata-Version: 2.2
Name: isage-tsdb
Version: 0.1.5
Summary: High-Performance Time Series Database with C++ Core
Author-Email: SAGE Team <shuhao_zhang@hust.edu.cn>
License: MIT
Classifier: Development Status :: 4 - Beta
Classifier: Intended Audience :: Developers
Classifier: Topic :: Software Development :: Libraries :: Python Modules
Classifier: Topic :: Database
Classifier: Topic :: Scientific/Engineering
Classifier: Programming Language :: Python :: 3
Classifier: Programming Language :: Python :: 3.10
Classifier: Programming Language :: Python :: 3.11
Classifier: Programming Language :: C++
Project-URL: Homepage, https://github.com/intellistream/sageTSDB
Project-URL: Repository, https://github.com/intellistream/sageTSDB.git
Project-URL: Bug Tracker, https://github.com/intellistream/sageTSDB/issues
Requires-Python: >=3.10
Requires-Dist: numpy<2.3.0,>=1.26.0
Provides-Extra: dev
Requires-Dist: pytest>=7.0.0; extra == "dev"
Requires-Dist: pytest-cov>=4.0.0; extra == "dev"
Requires-Dist: ruff>=0.1.0; extra == "dev"
